LICENSE.txt
MANIFEST.in
README.rst
setup.cfg
setup.py
pybridair/__init__.py
pybridair/auth.py
pybridair/conn.py
pybridair/data.py
pybridair/device.py
pybridair/objects.py
pybridair.egg-info/PKG-INFO
pybridair.egg-info/SOURCES.txt
pybridair.egg-info/dependency_links.txt
pybridair.egg-info/entry_points.txt
pybridair.egg-info/requires.txt
pybridair.egg-info/top_level.txt