Metadata-Version: 2.1
Name: pybridair
Version: 0.0.1
Summary: Python binding for Brid Smart Air Purifier Device API
Home-page: https://github.com/netmanchris/pybrid
Author: netmanchris
Author-email: chris_young@me.com
License: Apache2
Keywords: Brid Attelani
Platform: UNKNOWN
Classifier: Development Status :: 3 - Alpha
Classifier: Intended Audience :: Developers
Classifier: Intended Audience :: System Administrators
Classifier: License :: OSI Approved :: Apache Software License
Classifier: Programming Language :: Python
Classifier: Natural Language :: English
Classifier: Operating System :: OS Independent
Classifier: Topic :: Software Development :: Libraries :: Python Modules
Provides-Extra: dev
Provides-Extra: test
